securedai/__init__.py
securedai-0.1.1.dist-info/LICENSE.txt
securedai-0.1.1.dist-info/METADATA
securedai-0.1.1.dist-info/WHEEL
securedai-0.1.1.dist-info/top_level.txt
securedai-0.1.1.dist-info/RECORD
