Metadata-Version: 2.1
Name: securedai
Version: 0.1.1
Summary: Secure your ML models using securedai
Home-page: https://github.com/arristigit/securedai
Author: Varinder Kumar
License-File: LICENSE.txt
Requires-Dist: python-decouple==3.8
